django_delete_guard/apps.py
django_delete_guard/exceptions.py
django_delete_guard/guard.py
django_delete_guard/patch.py
django_delete_guard-0.1.1.dist-info/METADATA
django_delete_guard-0.1.1.dist-info/WHEEL
django_delete_guard-0.1.1.dist-info/RECORD
