Metadata-Version: 2.4
Name: django-delete-guard
Version: 0.1.1
Summary: Blocks dangerous Django ORM QuerySet.delete() calls in production.
Project-URL: Homepage, https://github.com/yourname/django-delete-guard
Project-URL: Repository, https://github.com/yourname/django-delete-guard
Project-URL: Issues, https://github.com/yourname/django-delete-guard/issues
Author: Matt
License: MIT
Keywords: delete,django,guard,orm,production,safety
Classifier: Development Status :: 3 - Alpha
Classifier: Framework :: Django
Classifier: Framework :: Django :: 3.2
Classifier: Framework :: Django :: 4.2
Classifier: Framework :: Django :: 5.0
Classifier: Framework :: Django :: 5.1
Classifier: License :: OSI Approved :: MIT License
Classifier: Programming Language :: Python :: 3
Classifier: Programming Language :: Python :: 3 :: Only
Requires-Python: >=3.9
Requires-Dist: django<6.0,>=3.2
Provides-Extra: dev
Requires-Dist: pytest-django>=4.8.0; extra == 'dev'
Requires-Dist: pytest>=8.0.0; extra == 'dev'
Requires-Dist: ruff>=0.5.0; extra == 'dev'
